balens/__init__.py
balens/binning.py
balens/cli.py
balens/detector.py
balens/exporter.py
balens/resampler.py
balens/weights.py
balens/__pycache__/__init__.cpython-312.pyc
balens/__pycache__/binning.cpython-312.pyc
balens/__pycache__/cli.cpython-312.pyc
balens/__pycache__/detector.cpython-312.pyc
balens/__pycache__/exporter.cpython-312.pyc
balens/__pycache__/resampler.cpython-312.pyc
balens/__pycache__/weights.cpython-312.pyc
balens-0.1.0.dist-info/licenses/LICENSE
balens-0.1.0.dist-info/METADATA
balens-0.1.0.dist-info/WHEEL
balens-0.1.0.dist-info/entry_points.txt
balens-0.1.0.dist-info/top_level.txt
balens-0.1.0.dist-info/RECORD
