Metadata-Version: 2.4
Name: balens
Version: 0.1.0
Summary: A universal Python toolkit for detecting and fixing data imbalance.
Author: Raktim Kalita
Author-email: Raktim Kalita <raktimkalita.ai@gmail.com>
License: MIT License
Project-URL: Homepage, https://github.com/yourusername/balens
Requires-Python: >=3.7
License-File: LICENSE
Requires-Dist: pandas
Requires-Dist: scikit-learn
Requires-Dist: imbalanced-learn
Requires-Dist: typer[all]
Dynamic: author
Dynamic: license-file
Dynamic: requires-python
